phonetisch/__init__.py
phonetisch/algorithms.py
phonetisch/utils.py
phonetisch-0.2.2.dist-info/LICENSE
phonetisch-0.2.2.dist-info/METADATA
phonetisch-0.2.2.dist-info/WHEEL
phonetisch-0.2.2.dist-info/top_level.txt
phonetisch-0.2.2.dist-info/RECORD
